msl/__init__.py
msl/examples/__init__.py
msl/examples/network/__init__.py
msl/examples/network/array.py
msl/examples/network/basic_math.py
msl/examples/network/dmm.py
msl/examples/network/echo.py
msl/examples/network/heartbeat.py
msl/network/__init__.py
msl/network/cli.py
msl/network/cli_argparse.py
msl/network/cli_certdump.py
msl/network/cli_certgen.py
msl/network/cli_delete.py
msl/network/cli_hostname.py
msl/network/cli_keygen.py
msl/network/cli_start.py
msl/network/cli_user.py
msl/network/client.py
msl/network/constants.py
msl/network/cryptography.py
msl/network/database.py
msl/network/json.py
msl/network/manager.py
msl/network/network.py
msl/network/service.py
msl/network/ssh.py
msl/network/utils.py
msl_network-1.0.0.dist-info/AUTHORS.rst
msl_network-1.0.0.dist-info/LICENSE.txt
msl_network-1.0.0.dist-info/METADATA
msl_network-1.0.0.dist-info/WHEEL
msl_network-1.0.0.dist-info/entry_points.txt
msl_network-1.0.0.dist-info/top_level.txt
msl_network-1.0.0.dist-info/RECORD
