Metadata-Version: 2.1
Name: msl-network
Version: 1.0.0
Summary: Concurrent and asynchronous network I/O
Home-page: https://github.com/MSLNZ/msl-network
Author: Measurement Standards Laboratory of New Zealand
Author-email: info@measurement.govt.nz
License: MIT
Platform: any
Classifier: Development Status :: 4 - Beta
Classifier: Intended Audience :: Science/Research
Classifier: Intended Audience :: Developers
Classifier: License :: OSI Approved :: MIT License
Classifier: Operating System :: OS Independent
Classifier: Programming Language :: Python
Classifier: Programming Language :: Python :: 3
Classifier: Programming Language :: Python :: 3.6
Classifier: Programming Language :: Python :: 3.7
Classifier: Programming Language :: Python :: 3.8
Classifier: Programming Language :: Python :: 3.9
Classifier: Programming Language :: Python :: 3.10
Classifier: Programming Language :: Python :: 3.11
Classifier: Topic :: Software Development
Classifier: Topic :: Scientific/Engineering
Requires-Python: >=3.6
License-File: LICENSE.txt
License-File: AUTHORS.rst
Requires-Dist: cryptography
Requires-Dist: paramiko
Provides-Extra: dev
Requires-Dist: pytest (>=4.4) ; extra == 'dev'
Requires-Dist: pytest-cov ; extra == 'dev'
Requires-Dist: python-rapidjson ; extra == 'dev'
Requires-Dist: simplejson ; extra == 'dev'
Requires-Dist: ujson ; extra == 'dev'
Requires-Dist: orjson ; extra == 'dev'
Requires-Dist: sphinx ; extra == 'dev'
Requires-Dist: sphinx-rtd-theme ; extra == 'dev'
Provides-Extra: docs
Requires-Dist: sphinx ; extra == 'docs'
Requires-Dist: sphinx-rtd-theme ; extra == 'docs'
Provides-Extra: tests
Requires-Dist: pytest (>=4.4) ; extra == 'tests'
Requires-Dist: pytest-cov ; extra == 'tests'
Requires-Dist: python-rapidjson ; extra == 'tests'
Requires-Dist: simplejson ; extra == 'tests'
Requires-Dist: ujson ; extra == 'tests'
Requires-Dist: orjson ; extra == 'tests'
